```java
public int foo() {
  ArrayList<Integer> list = new ArrayList<>();
  list.add(0);
  int result = list.get(0);
  return result;
}
```
```java

public int foo();
  Code:
     0: new java/util/ArrayList
     3: dup
     4: invokespecial java/util/ArrayList."<init>":()V
     7: astore_1
     8: aload_1
     9: iconst_0
		 //box
    10: invokestatic java/lang/Integer.valueOf:(I)Ljava/lang/Integer;
    13: invokevirtual java/util/ArrayList.add:(Ljava/lang/Object;)Z
    16: pop
    17: aload_1
    18: iconst_0
    19: invokevirtual java/util/ArrayList.get:(I)Ljava/lang/Object;
    22: checkcast java/lang/Integer
		//unbox
    25: invokevirtual java/lang/Integer.intValue:()I
    28: istore_2
    29: iload_2
    30: ireturn
```